{
  "project_info": {
    "project_number": "562323309629",
    "firebase_url": "https://bitmessenger-e4ab7.firebaseio.com",
    "project_id": "bitmessenger-e4ab7",
    "storage_bucket": "bitmessenger-e4ab7.appspot.com"
  },
  "client": [
    {
      "client_info": {
        "mobilesdk_app_id": "1:562323309629:android:02c3b4b2d7f6bfbec3d654",
        "android_client_info": {
          "package_name": "com.lxndxn.bitmessenger"
        }
      },
      "oauth_client": [
        {
          "client_id": "562323309629-03hh5ve14qg7aqti7mg6nah3vtr54ptr.apps.googleusercontent.com",
          "client_type": 3
        }
      ],
      "api_key": [
        {
          "current_key": "AIzaSyBWZH1mC79_BpkxtBqqeCXW6FU-G9t3eho"
        }
      ],
      "services": {
        "appinvite_service": {
          "other_platform_oauth_client": [
            {
              "client_id": "562323309629-03hh5ve14qg7aqti7mg6nah3vtr54ptr.apps.googleusercontent.com",
              "client_type": 3
            }
          ]
        }
      }
    }
  ],
  "configuration_version": "1"
}